red_logging-0.1.3.dist-info/METADATA
red_logging-0.1.3.dist-info/WHEEL
red_logging/__base.py
red_logging/__init__.py
red_logging/__methods.py
red_logging/config_classes/__init__.py
red_logging/config_classes/base/__init__.py
red_logging/config_classes/base/_base_config.py
red_logging/config_classes/base/_bases.py
red_logging/config_classes/formatters/__init__.py
red_logging/config_classes/formatters/_formatters.py
red_logging/config_classes/handlers/__init__.py
red_logging/config_classes/handlers/_handlers.py
red_logging/config_classes/loggers/__init__.py
red_logging/config_classes/loggers/_factory.py
red_logging/config_classes/loggers/_loggers.py
red_logging/config_classes/prefab/__init__.py
red_logging/config_classes/prefab/third_party/__init__.py
red_logging/config_classes/prefab/third_party/prefab_red_logging/__init__.py
red_logging/config_classes/prefab/third_party/prefab_red_logging/_configs.py
red_logging/config_classes/types.py
red_logging/filters/__init__.py
red_logging/filters/_filters.py
red_logging/filters/loglevel_filters/__init__.py
red_logging/filters/loglevel_filters/_loglevel_filters.py
red_logging/fmts/__init__.py
red_logging/fmts/_formats.py
red_logging/helpers/__init__.py
red_logging/helpers/__methods.py
red_logging-0.1.3.dist-info/RECORD
