Metadata-Version: 2.1
Name: red-logging
Version: 0.1.3
Summary: Helpful classes, functions, & utilities for the stdlib `logging` module. No external dependencies.
Author-Email: redjaxk <no@none.com>
License: MIT
Project-URL: Repository, https://github.com/redjax/red-logging
Project-URL: Documentation, https://red-logging.readthedocs.io/en/latest/
Project-URL: Download, https://pypi.org/project/red-logging/
Requires-Python: >=3.11
